cdktf_cdktf_provider_digitalocean/__init__.py
cdktf_cdktf_provider_digitalocean/py.typed
cdktf_cdktf_provider_digitalocean/_jsii/__init__.py
cdktf_cdktf_provider_digitalocean/_jsii/provider-digitalocean@13.12.0.jsii.tgz
cdktf_cdktf_provider_digitalocean/app/__init__.py
cdktf_cdktf_provider_digitalocean/cdn/__init__.py
cdktf_cdktf_provider_digitalocean/certificate/__init__.py
cdktf_cdktf_provider_digitalocean/container_registry/__init__.py
cdktf_cdktf_provider_digitalocean/container_registry_docker_credentials/__init__.py
cdktf_cdktf_provider_digitalocean/custom_image/__init__.py
cdktf_cdktf_provider_digitalocean/data_digitalocean_account/__init__.py
cdktf_cdktf_provider_digitalocean/data_digitalocean_app/__init__.py
cdktf_cdktf_provider_digitalocean/data_digitalocean_certificate/__init__.py
cdktf_cdktf_provider_digitalocean/data_digitalocean_container_registry/__init__.py
cdktf_cdktf_provider_digitalocean/data_digitalocean_database_ca/__init__.py
cdktf_cdktf_provider_digitalocean/data_digitalocean_database_cluster/__init__.py
cdktf_cdktf_provider_digitalocean/data_digitalocean_database_connection_pool/__init__.py
cdktf_cdktf_provider_digitalocean/data_digitalocean_database_metrics_credentials/__init__.py
cdktf_cdktf_provider_digitalocean/data_digitalocean_database_replica/__init__.py
cdktf_cdktf_provider_digitalocean/data_digitalocean_database_user/__init__.py
cdktf_cdktf_provider_digitalocean/data_digitalocean_domain/__init__.py
cdktf_cdktf_provider_digitalocean/data_digitalocean_domains/__init__.py
cdktf_cdktf_provider_digitalocean/data_digitalocean_droplet/__init__.py
cdktf_cdktf_provider_digitalocean/data_digitalocean_droplet_autoscale/__init__.py
cdktf_cdktf_provider_digitalocean/data_digitalocean_droplet_snapshot/__init__.py
cdktf_cdktf_provider_digitalocean/data_digitalocean_droplets/__init__.py
cdktf_cdktf_provider_digitalocean/data_digitalocean_firewall/__init__.py
cdktf_cdktf_provider_digitalocean/data_digitalocean_floating_ip/__init__.py
cdktf_cdktf_provider_digitalocean-13.12.0.dist-info/LICENSE
cdktf_cdktf_provider_digitalocean-13.12.0.dist-info/METADATA
cdktf_cdktf_provider_digitalocean-13.12.0.dist-info/WHEEL
cdktf_cdktf_provider_digitalocean-13.12.0.dist-info/top_level.txt
cdktf_cdktf_provider_digitalocean-13.12.0.dist-info/RECORD
